{
  "id": "373fcf0c-08aa-4918-a158-64bd3ac40825",
  "topic": "decision_control",
  "title": "Losing Control",
  "lesson": "lesson_2",
  "word_list": [
    {
      "id": "03d376a7-5e91-466e-aa5c-8cc47a929465",
      "word": "out of hand",
      "pos": "None",
      "phonetic": "https://tts.langeek.co/read?text=b3V0IG9mIGhhbmQ&hash=ab2ae0f18c78bd84a2c705208df955bc6596856f&lang=en&cache-only=0",
      "phonetic_text": "a ät  Ćv h√¶nd",
      "phonetic_am": "https://tts.langeek.co/read?text=b3V0IG9mIGhhbmQ&hash=ab2ae0f18c78bd84a2c705208df955bc6596856f&lang=en&cache-only=0",
      "phonetic_am_text": "aoot av hńĀnd",
      "img": "https://cdn.langeek.co/photo/44304/original/?type=jpeg",
      "pronunciation": "ňĆa ä…ĺ…ôv hňą√¶nd",
      "senses": [
        {
          "definition": "impossible or very hard to control",
          "examples": [
            {
              "cf": "",
              "x": "The party got out of hand when uninvited guests started causing trouble and breaking things."
            },
            {
              "cf": "",
              "x": "The argument between the coworkers quickly spiraled out of hand, with shouting and personal attacks."
            },
            {
              "cf": "",
              "x": "The children's playtime became out of hand when they started running around, knocking over furniture and making a mess."
            },
            {
              "cf": "",
              "x": "The negotiations between the two countries went out of hand when insults were exchanged and diplomatic talks broke down."
            }
          ]
        }
      ]
    },
    {
      "id": "6eb90045-1ab7-446a-8b06-02fc04a8304a",
      "word": "to [have] half a mind to",
      "pos": "None",
      "phonetic": "https://tts.langeek.co/read?text=dG8gaGF2ZSBoYWxmIGEgbWluZCB0bw&hash=3aaa4fe4d1e655b3b4b110016c74c1daa9d8f2ce&lang=en&cache-only=0",
      "phonetic_text": "",
      "phonetic_am": "https://tts.langeek.co/read?text=dG8gaGF2ZSBoYWxmIGEgbWluZCB0bw&hash=3aaa4fe4d1e655b3b4b110016c74c1daa9d8f2ce&lang=en&cache-only=0",
      "phonetic_am_text": null,
      "img": "https://cdn.langeek.co/photo/44468/original/?type=jpeg",
      "pronunciation": "h√¶v hňą√¶f …ź mňąa…™nd tuňź",
      "senses": [
        {
          "definition": "to say that one will do something even though they might not really intending to",
          "examples": [
            {
              "cf": "",
              "x": "I have half a mind to quit my job and pursue my true passion."
            },
            {
              "cf": "",
              "x": "They had half a mind to cancel the event due to the bad weather forecast."
            },
            {
              "cf": "",
              "x": "I have half a mind to sell all my belongings and travel the world."
            }
          ]
        }
      ]
    },
    {
      "id": "c1deb4be-308b-4986-81b7-8227e7af21ce",
      "word": "weak in the knees",
      "pos": "None",
      "phonetic": "https://tts.langeek.co/read?text=d2VhayBpbiB0aGUga25lZXM&hash=c72948fae057079d9f2dd05b5885118340532c41&lang=en&cache-only=0",
      "phonetic_text": "",
      "phonetic_am": "https://tts.langeek.co/read?text=d2VhayBpbiB0aGUga25lZXM&hash=c72948fae057079d9f2dd05b5885118340532c41&lang=en&cache-only=0",
      "phonetic_am_text": null,
      "img": "https://cdn.langeek.co/photo/44320/original/?type=jpeg",
      "pronunciation": "wňąiňźk …™n√į…ô nňąiňźz",
      "senses": [
        {
          "definition": "feeling strong emotions, like fear or anxiety, in a way that makes it difficult for one to stand",
          "examples": []
        }
      ]
    },
    {
      "id": "c903ce4f-5f0e-43af-b889-9634d61f0189",
      "word": "to [go] to town",
      "pos": "None",
      "phonetic": "https://tts.langeek.co/read?text=dG8gZ28gdG8gdG93bg&hash=ff767af27928d3a200113a09e699c022c4cb6917&lang=en&cache-only=0",
      "phonetic_text": "",
      "phonetic_am": "https://tts.langeek.co/read?text=dG8gZ28gdG8gdG93bg&hash=ff767af27928d3a200113a09e699c022c4cb6917&lang=en&cache-only=0",
      "phonetic_am_text": null,
      "img": "https://cdn.langeek.co/photo/43949/original/?type=jpeg",
      "pronunciation": "…°ňĆo ä t…ô tňąa än",
      "senses": [
        {
          "definition": "to engage in an activity or pursuit with great enthusiasm, energy, or extravagance, often to an excessive or intense degree",
          "examples": []
        }
      ]
    },
    {
      "id": "c1cc96ec-ea8f-4faf-bdd1-e96bd63ed516",
      "word": "to [keep] {one's} eyes off {sb/sth}",
      "pos": "None",
      "phonetic": "https://tts.langeek.co/read?text=dG8ga2VlcCBvbmUncyBleWVzIG9mZiBzb21lYm9keSBvciBzb21ldGhpbmc&hash=0b35088b985e2a3603668419601b17cdd17a76e6&lang=en&cache-only=0",
      "phonetic_text": "",
      "phonetic_am": "https://tts.langeek.co/read?text=dG8ga2VlcCBvbmUncyBleWVzIG9mZiBzb21lYm9keSBvciBzb21ldGhpbmc&hash=0b35088b985e2a3603668419601b17cdd17a76e6&lang=en&cache-only=0",
      "phonetic_am_text": null,
      "img": "https://cdn.langeek.co/photo/44300/original/?type=jpeg",
      "pronunciation": "kňąiňźp wňą Ćnz ňąa…™z ňą…Ēf ňĆ…õsbňąiňź slňą√¶ É ňĆ…õstňĆiňźňąe…™t É",
      "senses": [
        {
          "definition": "to refrain from or stop looking at a person or thing",
          "examples": []
        }
      ]
    },
    {
      "id": "06615115-2b7b-40ef-8ed5-39c15453322e",
      "word": "to [throw] {one's} (toys|rattle) out of the cot",
      "pos": "None",
      "phonetic": "https://tts.langeek.co/read?text=dG8gdGhyb3cgb25lJ3MgdG95cyBvdXQgb2YgdGhlIGNvdA&hash=7ab1114ff917ebd0cca8a337fd6ecce6bf8c29d3&lang=en&cache-only=0",
      "phonetic_text": "",
      "phonetic_am": "https://tts.langeek.co/read?text=dG8gdGhyb3cgb25lJ3MgdG95cyBvdXQgb2YgdGhlIGNvdA&hash=7ab1114ff917ebd0cca8a337fd6ecce6bf8c29d3&lang=en&cache-only=0",
      "phonetic_am_text": null,
      "img": "https://cdn.langeek.co/photo/42602/original/?type=jpeg",
      "pronunciation": "őł…Ļňąo ä wňą Ćnz tňą…Ē…™z …Ļňą√¶…ĺ…ôl ňĆa ä…ĺ…ôv √į…ô kňą…Ďňźt",
      "senses": [
        {
          "definition": "to lose one's temper and behave irrationally",
          "examples": []
        }
      ]
    },
    {
      "id": "24e51247-8f55-4235-96f0-3e692d7ff0bf",
      "word": "to [put] {one's} life in {one's} hands",
      "pos": "None",
      "phonetic": "https://tts.langeek.co/read?text=dG8gcHV0IG9uZSdzIGxpZmUgaW4gb25lJ3MgaGFuZHM&hash=05490c49c2776d78506fb68d56ccec156a0e4957&lang=en&cache-only=0",
      "phonetic_text": "",
      "phonetic_am": "https://tts.langeek.co/read?text=dG8gcHV0IG9uZSdzIGxpZmUgaW4gb25lJ3MgaGFuZHM&hash=05490c49c2776d78506fb68d56ccec156a0e4957&lang=en&cache-only=0",
      "phonetic_am_text": null,
      "img": "https://cdn.langeek.co/photo/44306/original/?type=jpeg",
      "pronunciation": "pňĆ ät wňą Ćnz lňąa…™f …™n wňą Ćnz hňą√¶ndz",
      "senses": [
        {
          "definition": "to entrust someone with one's life",
          "examples": []
        }
      ]
    },
    {
      "id": "8a999358-956c-434f-bd02-6602bfd06a4f",
      "word": "to [come] out (swinging|fighting)",
      "pos": "None",
      "phonetic": "https://tts.langeek.co/read?text=dG8gY29tZSBvdXQgc3dpbmdpbmc&hash=d98d40eb885689539cbd56510e78b40533110eaa&lang=en&cache-only=0",
      "phonetic_text": "",
      "phonetic_am": "https://tts.langeek.co/read?text=dG8gY29tZSBvdXQgc3dpbmdpbmc&hash=d98d40eb885689539cbd56510e78b40533110eaa&lang=en&cache-only=0",
      "phonetic_am_text": null,
      "img": "https://cdn.langeek.co/photo/26461/original/?type=jpeg",
      "pronunciation": "kňą Ćm ňąa ät swňą…™Ňč…™Ňč fňą…Ďňź…ĺ…™Ňč",
      "senses": [
        {
          "definition": "to respond or react to something in a forceful manner",
          "examples": []
        }
      ]
    },
    {
      "id": "b0797411-b94c-4a3d-b9a8-451aafb7f4b5",
      "word": "to [get|be] carried away",
      "pos": "None",
      "phonetic": "https://tts.langeek.co/read?text=dG8gZ2V0IGNhcnJpZWQgYXdheQ&hash=a134c0964a417a5d7542b4ca6da03d2759db43ce&lang=en&cache-only=0",
      "phonetic_text": "",
      "phonetic_am": "https://tts.langeek.co/read?text=dG8gZ2V0IGNhcnJpZWQgYXdheQ&hash=a134c0964a417a5d7542b4ca6da03d2759db43ce&lang=en&cache-only=0",
      "phonetic_am_text": null,
      "img": "https://cdn.langeek.co/photo/44734/original/?type=jpeg",
      "pronunciation": "…°…õt …Ēňź…Ļ biňź kňą√¶…Ļ…™d …źwňąe…™",
      "senses": [
        {
          "definition": "to be unable to control one's behavior due to a strong emotion such as anger, excitement, etc.",
          "examples": [
            {
              "cf": "",
              "x": "She was so caught up in the moment that she was carried away by the applause and forgot her next line."
            },
            {
              "cf": "",
              "x": "He was carried away by the emotions of the romantic movie and couldn't help but shed a tear."
            },
            {
              "cf": "",
              "x": "While singing karaoke, she got carried away with the music and belted out the song at the top of her lungs."
            },
            {
              "cf": "",
              "x": "During the debate, he got carried away with his argument and spoke for far longer than he had intended."
            }
          ]
        }
      ]
    },
    {
      "id": "8e84f6d3-3bca-462a-b2c6-c47df4525578",
      "word": "off the rails",
      "pos": "None",
      "phonetic": "https://tts.langeek.co/read?text=b2ZmIHRoZSByYWlscw&hash=3be714b55a5dfae0efdc8579f5fe53b3a5619421&lang=en&cache-only=0",
      "phonetic_text": "…Ďf √į…ô re…™lz",
      "phonetic_am": "https://tts.langeek.co/read?text=b2ZmIHRoZSByYWlscw&hash=3be714b55a5dfae0efdc8579f5fe53b3a5619421&lang=en&cache-only=0",
      "phonetic_am_text": "aaf dhńď reilz",
      "img": "https://cdn.langeek.co/photo/42018/original/?type=jpeg",
      "pronunciation": "ňą…Ēf √į…ô …Ļňąe…™lz",
      "senses": [
        {
          "definition": "used to say that someone is behaving in a way that is wild, irrational, or unconventional",
          "examples": []
        }
      ]
    },
    {
      "id": "0f5ad10b-e939-44fe-b087-d5d818525da3",
      "word": "to [hit|press|push] the panic button",
      "pos": "None",
      "phonetic": "https://tts.langeek.co/read?text=dG8gaGl0IHRoZSBwYW5pYyBidXR0b24&hash=102ac426c22086e7a32eb121ff50bfdd95566b5d&lang=en&cache-only=0",
      "phonetic_text": "",
      "phonetic_am": "https://tts.langeek.co/read?text=dG8gaGl0IHRoZSBwYW5pYyBidXR0b24&hash=102ac426c22086e7a32eb121ff50bfdd95566b5d&lang=en&cache-only=0",
      "phonetic_am_text": null,
      "img": "https://cdn.langeek.co/photo/42790/original/?type=jpeg",
      "pronunciation": "hňą…™t p…Ļňą…õs pňą ä É √į…ô pňą√¶n…™k bňą Ć ĒnŐ©",
      "senses": [
        {
          "definition": "to panic or respond with extreme fear or urgency in a situation, often without thinking logically or rationally",
          "examples": []
        }
      ]
    }
  ]
}