{
  "id": "84992d43-cfb0-48f1-a915-f303e496a524",
  "topic": "personal_care",
  "title": "Hair Removal",
  "lesson": "lesson_7",
  "word_list": [
    {
      "id": "85729772-7edc-4602-acc8-5ed3922d3d60",
      "word": "grooming",
      "pos": "noun",
      "phonetic": "https://tts.langeek.co/read?text=Z3Jvb21pbmc&hash=ed5af81ff29cfc3e9b770d614ad4c7bb1872f690&lang=en&cache-only=0",
      "phonetic_text": "gru.mɪng",
      "phonetic_am": "https://tts.langeek.co/read?text=Z3Jvb21pbmc&hash=ed5af81ff29cfc3e9b770d614ad4c7bb1872f690&lang=en&cache-only=0",
      "phonetic_am_text": "groo.ming",
      "img": "https://cdn.langeek.co/photo/26128/original/?type=jpeg",
      "pronunciation": "ˈɡɹumɪŋ",
      "senses": [
        {
          "definition": "the activity of keeping tidy and neat by brushing hair, keeping clothes clean, etc.",
          "examples": []
        }
      ]
    },
    {
      "id": "49f3f74d-e31b-46c8-a164-b3569aa84170",
      "word": "trimming",
      "pos": "noun",
      "phonetic": "https://tts.langeek.co/read?text=dHJpbW1pbmc&hash=424e43df0bb4f171389b78cc88102adc69c68da8&lang=en&cache-only=0",
      "phonetic_text": "trɪ.mɪng",
      "phonetic_am": "https://tts.langeek.co/read?text=dHJpbW1pbmc&hash=424e43df0bb4f171389b78cc88102adc69c68da8&lang=en&cache-only=0",
      "phonetic_am_text": "tri.ming",
      "img": "",
      "pronunciation": "ˈtɹɪmɪŋ",
      "senses": [
        {
          "definition": "the act of cutting small amounts of hair to maintain or shape its length, usually to remove split ends",
          "examples": []
        }
      ]
    },
    {
      "id": "b4d918f7-bfef-4703-b6ea-44d0df2492a0",
      "word": "to wax",
      "pos": "verb",
      "phonetic": "https://tts.langeek.co/read?text=dG8gd2F4&hash=835cac578d1a23b047c19c5b754cacfb63ccf960&lang=en&cache-only=0",
      "phonetic_text": "wæks",
      "phonetic_am": "https://tts.langeek.co/read?text=dG8gd2F4&hash=835cac578d1a23b047c19c5b754cacfb63ccf960&lang=en&cache-only=0",
      "phonetic_am_text": "vāks",
      "img": "https://cdn.langeek.co/photo/33006/original/?type=jpeg",
      "pronunciation": "ˈwæks",
      "senses": [
        {
          "definition": "to use a thin and warm layer of a substance that is usually made of beeswax to remove unwanted hair from the skin",
          "examples": []
        }
      ]
    },
    {
      "id": "490eb64d-9976-4d18-a94f-6865d3687ea2",
      "word": "waxing",
      "pos": "noun",
      "phonetic": "https://tts.langeek.co/read?text=d2F4aW5n&hash=ebeaa62cb6da93e25c84cba1e70b77c6012665dd&lang=en&cache-only=0",
      "phonetic_text": "wæk.sɪng",
      "phonetic_am": "https://tts.langeek.co/read?text=d2F4aW5n&hash=ebeaa62cb6da93e25c84cba1e70b77c6012665dd&lang=en&cache-only=0",
      "phonetic_am_text": "vāk.sing",
      "img": "",
      "pronunciation": "ˈwæksɪŋ",
      "senses": [
        {
          "definition": "a hair removal technique that involves applying and removing wax to eliminate unwanted hair from the root",
          "examples": []
        }
      ]
    },
    {
      "id": "90cb3471-6786-4fb1-98d1-57406d8b2866",
      "word": "laser hair removal",
      "pos": "noun",
      "phonetic": "https://tts.langeek.co/read?text=bGFzZXIgaGFpciByZW1vdmFs&hash=6fdd49fdea264d79a0b9ed8497629c460987bdbb&lang=en&cache-only=0",
      "phonetic_text": "leɪ.zɜr hɛr rɪ.mu.vəl",
      "phonetic_am": "https://tts.langeek.co/read?text=bGFzZXIgaGFpciByZW1vdmFs&hash=6fdd49fdea264d79a0b9ed8497629c460987bdbb&lang=en&cache-only=0",
      "phonetic_am_text": "lei.zēr her ri.moo.vēl",
      "img": "",
      "pronunciation": "leɪzɚ hɛɹ ɹɪmuːvəl",
      "senses": [
        {
          "definition": "a cosmetic procedure that uses lasers to inhibit hair growth by targeting and damaging hair follicles, providing a longer-lasting solution for unwanted body or facial hair",
          "examples": []
        }
      ]
    },
    {
      "id": "b930be88-313e-47a4-b1a7-f0c244f436d8",
      "word": "electrolysis",
      "pos": "noun",
      "phonetic": "https://tts.langeek.co/read?text=ZWxlY3Ryb2x5c2lz&hash=4df9af19b41f8b2b6f4881d3338aff66c0cf5a3d&lang=en&cache-only=0",
      "phonetic_text": "ɪ.lɛkt.rɑ.lə.səs",
      "phonetic_am": "https://tts.langeek.co/read?text=ZWxlY3Ryb2x5c2lz&hash=4df9af19b41f8b2b6f4881d3338aff66c0cf5a3d&lang=en&cache-only=0",
      "phonetic_am_text": "i.lekt.raa.lē.sēs",
      "img": "",
      "pronunciation": "ɪˌɫɛkˈtɹɑɫəsəs",
      "senses": [
        {
          "definition": "a method of permanent hair removal that uses electric currents to destroy hair follicles",
          "examples": [
            {
              "cf": "",
              "x": "She decided to undergo electrolysis to achieve long-lasting hair removal and enjoy smooth skin."
            },
            {
              "cf": "",
              "x": "After several electrolysis sessions, he experienced significant hair reduction and increased self-confidence."
            },
            {
              "cf": "",
              "x": "Many individuals opt for electrolysis as a reliable solution for permanent hair removal."
            }
          ]
        }
      ]
    },
    {
      "id": "d445b97a-a299-4231-840b-249c43ac3952",
      "word": "intense pulsed light",
      "pos": "noun",
      "phonetic": "https://tts.langeek.co/read?text=aW50ZW5zZSBwdWxzZWQgbGlnaHQ&hash=b25d2fd05caad52948143615cc0e7a52f60b0cc2&lang=en&cache-only=0",
      "phonetic_text": "",
      "phonetic_am": "https://tts.langeek.co/read?text=aW50ZW5zZSBwdWxzZWQgbGlnaHQ&hash=b25d2fd05caad52948143615cc0e7a52f60b0cc2&lang=en&cache-only=0",
      "phonetic_am_text": null,
      "img": "",
      "pronunciation": "ɪntɛns pʌlzd laɪt",
      "senses": [
        {
          "definition": "a cosmetic treatment that uses broad-spectrum light to target and treat skin conditions without harming surrounding tissue",
          "examples": []
        }
      ]
    },
    {
      "id": "1bb3fb7d-d33e-456f-a646-1eb1e0e4dd5c",
      "word": "epilation",
      "pos": "noun",
      "phonetic": "https://tts.langeek.co/read?text=ZXBpbGF0aW9u&hash=f152b1495601c5a8e6490d7f6e0fc8f0231e1d07&lang=en&cache-only=0",
      "phonetic_text": "ɛ.pɪ.leɪ.ʃən",
      "phonetic_am": "https://tts.langeek.co/read?text=ZXBpbGF0aW9u&hash=f152b1495601c5a8e6490d7f6e0fc8f0231e1d07&lang=en&cache-only=0",
      "phonetic_am_text": "e.pi.lei.shēn",
      "img": "",
      "pronunciation": "ˌɛpɪlˈeɪʃən",
      "senses": [
        {
          "definition": "the removal of hair from the root, resulting in longer-lasting hair-free skin",
          "examples": []
        }
      ]
    },
    {
      "id": "864770c1-8db3-45f6-baae-2da87bfd6a9f",
      "word": "depilatory",
      "pos": "noun",
      "phonetic": "https://tts.langeek.co/read?text=ZGVwaWxhdG9yeQ&hash=9eff98b52e4649d3d108b5511c6eefae6be426a7&lang=en&cache-only=0",
      "phonetic_text": "dɪ.pɪ.lə.tɔ.ri",
      "phonetic_am": "https://tts.langeek.co/read?text=ZGVwaWxhdG9yeQ&hash=9eff98b52e4649d3d108b5511c6eefae6be426a7&lang=en&cache-only=0",
      "phonetic_am_text": "di.pi.lē.taw.ri",
      "img": "https://cdn.langeek.co/photo/29854/original/?type=jpeg",
      "pronunciation": "dɪˈpɪɫəˌtɔɹi",
      "senses": [
        {
          "definition": "a substance applied to the skin in order to remove unwanted hair",
          "examples": []
        }
      ]
    },
    {
      "id": "90a3011c-e159-444e-8fa7-3b13ca266e10",
      "word": "shaving",
      "pos": "noun",
      "phonetic": "https://tts.langeek.co/read?text=c2hhdmluZw&hash=e778d4ace6eca6c65b1183291ff2f04f4e88491e&lang=en&cache-only=0",
      "phonetic_text": "ʃeɪ.vɪng",
      "phonetic_am": "https://tts.langeek.co/read?text=c2hhdmluZw&hash=e778d4ace6eca6c65b1183291ff2f04f4e88491e&lang=en&cache-only=0",
      "phonetic_am_text": "shei.ving",
      "img": "",
      "pronunciation": "ˈʃeɪvɪŋ",
      "senses": [
        {
          "definition": "the act of removing hair from the body or face using a razor or similar tool, typically by cutting the hair at the skin's surface",
          "examples": []
        }
      ]
    },
    {
      "id": "38b19827-5e24-45ca-93e3-217a77548a0d",
      "word": "to shave",
      "pos": "verb",
      "phonetic": "https://tts.langeek.co/read?text=dG8gc2hhdmU&hash=d268f8e696d4bdf081fef892c14c7c46903c6f62&lang=en&cache-only=0",
      "phonetic_text": "ʃeɪv",
      "phonetic_am": "https://tts.langeek.co/read?text=dG8gc2hhdmU&hash=d268f8e696d4bdf081fef892c14c7c46903c6f62&lang=en&cache-only=0",
      "phonetic_am_text": "sheiv",
      "img": "https://cdn.langeek.co/photo/17391/original/shave?type=jpeg",
      "pronunciation": "ʃeɪv",
      "senses": [
        {
          "definition": "to remove hair from the body using a razor or similar tool",
          "examples": [
            {
              "cf": "",
              "x": "He shaves his face every morning to keep it smooth."
            },
            {
              "cf": "",
              "x": "She shaves her legs regularly to maintain smooth skin."
            },
            {
              "cf": "",
              "x": "The barber shaved the customer's face with precision."
            },
            {
              "cf": "",
              "x": "After swimming, he shaves his armpits for better hygiene."
            }
          ]
        }
      ]
    },
    {
      "id": "0284bdb4-64d3-408d-8509-6db6614a3029",
      "word": "aftershave",
      "pos": "noun",
      "phonetic": "https://tts.langeek.co/read?text=YWZ0ZXJzaGF2ZQ&hash=e22eb5fb1ec740e33c6321ff13eef0ec7ddd7f30&lang=en&cache-only=0",
      "phonetic_text": "æf.tər.ʃeɪv",
      "phonetic_am": "https://tts.langeek.co/read?text=YWZ0ZXJzaGF2ZQ&hash=e22eb5fb1ec740e33c6321ff13eef0ec7ddd7f30&lang=en&cache-only=0",
      "phonetic_am_text": "āf.tēr.sheiv",
      "img": "https://cdn.langeek.co/photo/35615/original/?type=jpeg",
      "pronunciation": "ˈæftɚʃˈeɪv",
      "senses": [
        {
          "definition": "a fragrant liquid or lotion that is applied to the skin after being shaved, particularly used by men",
          "examples": [
            {
              "cf": "",
              "x": "The aftershave has a refreshing citrus scent."
            },
            {
              "cf": "",
              "x": "The store sells aftershave balms for sensitive skin."
            },
            {
              "cf": "",
              "x": "He forgot to pack his aftershave for the trip."
            },
            {
              "cf": "",
              "x": "The barber applied a soothing aftershave to his freshly shaved face."
            },
            {
              "cf": "",
              "x": "He prefers alcohol-free aftershave to avoid dryness."
            }
          ]
        }
      ]
    },
    {
      "id": "20124216-2a0b-4883-a5a6-69191092a427",
      "word": "bikini line",
      "pos": "noun",
      "phonetic": "https://tts.langeek.co/read?text=YmlraW5pIGxpbmU&hash=ca099a77fd14a2e0908c0dc8cd0cbe50fbdd5137&lang=en&cache-only=0",
      "phonetic_text": "bɪ.ki.ni laɪn",
      "phonetic_am": "https://tts.langeek.co/read?text=YmlraW5pIGxpbmU&hash=ca099a77fd14a2e0908c0dc8cd0cbe50fbdd5137&lang=en&cache-only=0",
      "phonetic_am_text": "bi.ki.ni lain",
      "img": "",
      "pronunciation": "bɪkiːni laɪn",
      "senses": [
        {
          "definition": "the pubic region where hair removal or grooming is done to shape or remove visible hair while wearing a bikini or swimwear",
          "examples": []
        }
      ]
    },
    {
      "id": "dbf594a1-5b8d-433a-b146-42e83476e4a0",
      "word": "depilatory",
      "pos": "adjective",
      "phonetic": "https://tts.langeek.co/read?text=ZGVwaWxhdG9yeQ&hash=9eff98b52e4649d3d108b5511c6eefae6be426a7&lang=en&cache-only=0",
      "phonetic_text": "dɪ.pɪ.lə.tɔ.ri",
      "phonetic_am": "https://tts.langeek.co/read?text=ZGVwaWxhdG9yeQ&hash=9eff98b52e4649d3d108b5511c6eefae6be426a7&lang=en&cache-only=0",
      "phonetic_am_text": "di.pi.lē.taw.ri",
      "img": "https://cdn.langeek.co/photo/29854/original/?type=jpeg",
      "pronunciation": "dɪˈpɪɫəˌtɔɹi",
      "senses": [
        {
          "definition": "used for the removal of undesired body hair",
          "examples": []
        }
      ]
    },
    {
      "id": "cbd1589c-d3c1-4649-80e0-c9299eed190a",
      "word": "to pluck",
      "pos": "verb",
      "phonetic": "https://tts.langeek.co/read?text=dG8gcGx1Y2s&hash=ddeccdf1b8016208b380349b98b652939992f074&lang=en&cache-only=0",
      "phonetic_text": "plək",
      "phonetic_am": "https://tts.langeek.co/read?text=dG8gcGx1Y2s&hash=ddeccdf1b8016208b380349b98b652939992f074&lang=en&cache-only=0",
      "phonetic_am_text": "plēk",
      "img": "",
      "pronunciation": "ˈpɫək",
      "senses": [
        {
          "definition": "to remove stray hairs from the eyebrows for grooming or shaping purposes",
          "examples": [
            {
              "cf": "",
              "x": "She plucked her eyebrows to create a defined arch that framed her eyes beautifully."
            },
            {
              "cf": "",
              "x": "After noticing a few unruly hairs, she decided to pluck her eyebrows to maintain a polished look."
            },
            {
              "cf": "",
              "x": "As part of her beauty routine, she regularly plucked her eyebrows to keep them well-groomed."
            },
            {
              "cf": "",
              "x": "The makeup artist plucked the model's eyebrows to create a precise and symmetrical shape."
            }
          ]
        }
      ]
    },
    {
      "id": "97743c73-ebc5-4992-9e56-5a24c48fe75c",
      "word": "razor",
      "pos": "noun",
      "phonetic": "https://tts.langeek.co/read?text=cmF6b3I&hash=69de51f9700e064faa637cb4550e84df48637970&lang=en&cache-only=0",
      "phonetic_text": "reɪ.zɜr",
      "phonetic_am": "https://tts.langeek.co/read?text=cmF6b3I&hash=69de51f9700e064faa637cb4550e84df48637970&lang=en&cache-only=0",
      "phonetic_am_text": "rei.zēr",
      "img": "https://cdn.langeek.co/photo/61520/original/razor?type=jpeg",
      "pronunciation": "ˈreɪzɚ",
      "senses": [
        {
          "definition": "a sharp-edged tool used for shaving hair off the body or face",
          "examples": [
            {
              "cf": "",
              "x": "She replaced the blades in her disposable razor for a smooth shave."
            },
            {
              "cf": "",
              "x": "They stocked up on razors and shaving cream at the store."
            },
            {
              "cf": "",
              "x": "He nicked himself with the razor while shaving and applied a small bandage."
            }
          ]
        }
      ]
    },
    {
      "id": "d7091c8c-1c0e-4fe0-8466-16121e057481",
      "word": "shaver",
      "pos": "noun",
      "phonetic": "https://tts.langeek.co/read?text=c2hhdmVy&hash=5b55f669f81da43eecd9f8902a774682e57a9acb&lang=en&cache-only=0",
      "phonetic_text": "ʃeɪ.vɜr",
      "phonetic_am": "https://tts.langeek.co/read?text=c2hhdmVy&hash=5b55f669f81da43eecd9f8902a774682e57a9acb&lang=en&cache-only=0",
      "phonetic_am_text": "shei.vēr",
      "img": "https://cdn.langeek.co/photo/22975/original/?type=jpeg",
      "pronunciation": "ˈʃeɪvɝ",
      "senses": [
        {
          "definition": "an electric tool used for shaving",
          "examples": [
            {
              "cf": "",
              "x": "He decided to use a shaver for a quick and convenient grooming routine."
            },
            {
              "cf": "",
              "x": "The shaver's blades are designed for a close and comfortable shave."
            },
            {
              "cf": "",
              "x": "He invested in a high-quality shaver for a smoother finish."
            },
            {
              "cf": "",
              "x": "The shaver comes with a cleaning brush for easy maintenance."
            }
          ]
        }
      ]
    },
    {
      "id": "c113dc91-2bb9-4721-ae6c-a3234b802df6",
      "word": "to razor",
      "pos": "verb",
      "phonetic": "https://tts.langeek.co/read?text=dG8gcmF6b3I&hash=0e2a01fd68c084319357b5baf361e32671e85089&lang=en&cache-only=0",
      "phonetic_text": "reɪ.zɜr",
      "phonetic_am": "https://tts.langeek.co/read?text=dG8gcmF6b3I&hash=0e2a01fd68c084319357b5baf361e32671e85089&lang=en&cache-only=0",
      "phonetic_am_text": "rei.zēr",
      "img": "",
      "pronunciation": "ˈreɪzɚ",
      "senses": [
        {
          "definition": "to shave or remove hair from the body using a razor or sharp-edged tool",
          "examples": []
        }
      ]
    },
    {
      "id": "3301e9b1-7b0d-40ee-9c6a-affd2dd0e9fe",
      "word": "safety razor",
      "pos": "noun",
      "phonetic": "https://tts.langeek.co/read?text=c2FmZXR5IHJhem9y&hash=2a9420da5f2378a0e40a0e2af3b110824f3aee19&lang=en&cache-only=0",
      "phonetic_text": "seɪf.ti reɪ.zɜr",
      "phonetic_am": "https://tts.langeek.co/read?text=c2FmZXR5IHJhem9y&hash=2a9420da5f2378a0e40a0e2af3b110824f3aee19&lang=en&cache-only=0",
      "phonetic_am_text": "seif.ti rei.zēr",
      "img": "",
      "pronunciation": "sˈeɪfti ɹˈeɪzɚ",
      "senses": [
        {
          "definition": "a type of razor with a protective guard between the blade and the skin to reduce the risk of cuts",
          "examples": []
        }
      ]
    },
    {
      "id": "2fc04233-79db-4d20-9616-d6e9238b24ac",
      "word": "shaving brush",
      "pos": "noun",
      "phonetic": "https://tts.langeek.co/read?text=c2hhdmluZyBicnVzaA&hash=f8c397afe9375c84ad7d7918c0a8e5c8498170cb&lang=en&cache-only=0",
      "phonetic_text": "ʃeɪ.vɪng brʌʃ",
      "phonetic_am": "https://tts.langeek.co/read?text=c2hhdmluZyBicnVzaA&hash=f8c397afe9375c84ad7d7918c0a8e5c8498170cb&lang=en&cache-only=0",
      "phonetic_am_text": "shei.ving brash",
      "img": "",
      "pronunciation": "ʃˈeɪvɪŋ bɹˈʌʃ",
      "senses": [
        {
          "definition": "a personal care tool with bristles used to apply shaving cream or soap to the face",
          "examples": []
        }
      ]
    },
    {
      "id": "24c936fb-6c65-42f8-b1a0-8f957840684e",
      "word": "shaving cream",
      "pos": "noun",
      "phonetic": "https://tts.langeek.co/read?text=c2hhdmluZyBjcmVhbQ&hash=c0d9cbf3fc23aa1f093cb9a6a720a802bbface04&lang=en&cache-only=0",
      "phonetic_text": "ʃeɪ.vɪng kri:m",
      "phonetic_am": "https://tts.langeek.co/read?text=c2hhdmluZyBjcmVhbQ&hash=c0d9cbf3fc23aa1f093cb9a6a720a802bbface04&lang=en&cache-only=0",
      "phonetic_am_text": "shei.ving krim",
      "img": "https://cdn.langeek.co/photo/35645/original/?type=jpeg",
      "pronunciation": "ʃˈeɪvɪŋ kɹˈiːm",
      "senses": [
        {
          "definition": "special product applied to one's face or other body parts before shaving",
          "examples": [
            {
              "cf": "",
              "x": "He applied shaving cream before using the razor."
            },
            {
              "cf": "",
              "x": "The store sells shaving cream in various scents and formulas."
            },
            {
              "cf": "",
              "x": "The shaving cream helps prevent cuts and irritation."
            },
            {
              "cf": "",
              "x": "They make shaving cream for sensitive skin to avoid redness."
            },
            {
              "cf": "",
              "x": "She bought a can of shaving cream for her husband."
            }
          ]
        }
      ]
    },
    {
      "id": "1cfe2745-0e56-4001-983c-1a2e0651fa99",
      "word": "wax",
      "pos": "noun",
      "phonetic": "https://tts.langeek.co/read?text=d2F4&hash=5478e2c57a69642c28d6b1463223aa042bc66c86&lang=en&cache-only=0",
      "phonetic_text": "wæks",
      "phonetic_am": "https://tts.langeek.co/read?text=d2F4&hash=5478e2c57a69642c28d6b1463223aa042bc66c86&lang=en&cache-only=0",
      "phonetic_am_text": "vāks",
      "img": "",
      "pronunciation": "ˈwæks",
      "senses": [
        {
          "definition": "a solid, fatty substance that is typically melted to make candles, used for coating surfaces or as a component of certain cosmetic or medical products",
          "examples": [
            {
              "cf": "",
              "x": "She melted the wax to make candles."
            },
            {
              "cf": "",
              "x": "The floor was polished with a layer of wax."
            },
            {
              "cf": "",
              "x": "He used wax to seal the envelope."
            },
            {
              "cf": "",
              "x": "Bees produce natural wax for their honeycombs."
            },
            {
              "cf": "",
              "x": "The wax on the surfboard helped with grip."
            }
          ]
        }
      ]
    },
    {
      "id": "40764487-e595-48d1-ab48-7cde5e842a56",
      "word": "wax warmer",
      "pos": "noun",
      "phonetic": "https://tts.langeek.co/read?text=d2F4IHdhcm1lcg&hash=6a37ec245f7481eb0b7b9dca0cf95febfe8ef6a9&lang=en&cache-only=0",
      "phonetic_text": "wæks wɔr.mɜr",
      "phonetic_am": "https://tts.langeek.co/read?text=d2F4IHdhcm1lcg&hash=6a37ec245f7481eb0b7b9dca0cf95febfe8ef6a9&lang=en&cache-only=0",
      "phonetic_am_text": "vāks vawr.mēr",
      "img": "",
      "pronunciation": "wæks wɔːɹmɚ",
      "senses": [
        {
          "definition": "a device used in beauty and spa settings to heat wax for various waxing treatments by keeping the wax in a liquid state for easy application",
          "examples": []
        }
      ]
    },
    {
      "id": "836e7eb4-1c92-4e04-a885-97af3b3af759",
      "word": "hair removal spray foam",
      "pos": "noun",
      "phonetic": "https://tts.langeek.co/read?text=aGFpciByZW1vdmFsIHNwcmF5IGZvYW0&hash=5530faa68ecb7b9a023b78ed4fdb4a05b3b91efd&lang=en&cache-only=0",
      "phonetic_text": "hɛr rɪ.mu.vəl spreɪ foʊm",
      "phonetic_am": "https://tts.langeek.co/read?text=aGFpciByZW1vdmFsIHNwcmF5IGZvYW0&hash=5530faa68ecb7b9a023b78ed4fdb4a05b3b91efd&lang=en&cache-only=0",
      "phonetic_am_text": "her ri.moo.vēl sprei fooom",
      "img": "",
      "pronunciation": "hɛɹ ɹɪmuːvəl spɹeɪ foʊm",
      "senses": [
        {
          "definition": "a depilatory product that dissolves or weakens hair for easy removal, typically coming in a foam form for convenient application",
          "examples": []
        }
      ]
    },
    {
      "id": "bd4e0659-86aa-4591-a6b2-a648be8c9f55",
      "word": "hair remover gel cream",
      "pos": "noun",
      "phonetic": "https://tts.langeek.co/read?text=aGFpciByZW1vdmVyIGdlbCBjcmVhbQ&hash=425065fa86f0aeeb9827dee00af2ccfc3b9a4083&lang=en&cache-only=0",
      "phonetic_text": "hɛr rɪ.mu.vɜr ʤɛl kri:m",
      "phonetic_am": "https://tts.langeek.co/read?text=aGFpciByZW1vdmVyIGdlbCBjcmVhbQ&hash=425065fa86f0aeeb9827dee00af2ccfc3b9a4083&lang=en&cache-only=0",
      "phonetic_am_text": "her ri.moo.vēr jel krim",
      "img": "",
      "pronunciation": "hɛɹ ɹɪmuːvɚ dʒɛl kɹiːm",
      "senses": [
        {
          "definition": "a depilatory cream that removes hair by dissolving or weakening it, providing a temporary hair removal solution",
          "examples": []
        }
      ]
    },
    {
      "id": "b2eea180-f66f-483f-8e6b-36d9fb2922c8",
      "word": "hair removal cream",
      "pos": "noun",
      "phonetic": "https://tts.langeek.co/read?text=aGFpciByZW1vdmFsIGNyZWFt&hash=0841990e46c9f410cfad6496624c831e7c0af503&lang=en&cache-only=0",
      "phonetic_text": "hɛr rɪ.mu.vəl kri:m",
      "phonetic_am": "https://tts.langeek.co/read?text=aGFpciByZW1vdmFsIGNyZWFt&hash=0841990e46c9f410cfad6496624c831e7c0af503&lang=en&cache-only=0",
      "phonetic_am_text": "her ri.moo.vēl krim",
      "img": "",
      "pronunciation": "hɛɹ ɹɪmuːvəl kɹiːm",
      "senses": [
        {
          "definition": "a depilatory product that dissolves or weakens hair for temporary removal from the skin's surface",
          "examples": []
        }
      ]
    },
    {
      "id": "13e66480-9144-4d90-9dbf-10fad4d8a737",
      "word": "depilatory cream",
      "pos": "noun",
      "phonetic": "https://tts.langeek.co/read?text=ZGVwaWxhdG9yeSBjcmVhbQ&hash=8e5e1e02834fade600a8b115697cda7470ac3547&lang=en&cache-only=0",
      "phonetic_text": "dɪ.pɪ.lə.tɔ.ri kri:m",
      "phonetic_am": "https://tts.langeek.co/read?text=ZGVwaWxhdG9yeSBjcmVhbQ&hash=8e5e1e02834fade600a8b115697cda7470ac3547&lang=en&cache-only=0",
      "phonetic_am_text": "di.pi.lē.taw.ri krim",
      "img": "",
      "pronunciation": "dɪpɪlətoːɹi kɹiːm",
      "senses": [
        {
          "definition": "a product used for temporary hair removal that typically comes in cream form",
          "examples": []
        }
      ]
    },
    {
      "id": "9db9fcce-a427-4826-9f5d-1d6eac009bc4",
      "word": "epilator",
      "pos": "noun",
      "phonetic": "https://tts.langeek.co/read?text=ZXBpbGF0b3I&hash=3b71b627cf5cf03ed52f043827804ccf333abc5c&lang=en&cache-only=0",
      "phonetic_text": "ɛ.pɪ.leɪ.tər",
      "phonetic_am": "https://tts.langeek.co/read?text=ZXBpbGF0b3I&hash=3b71b627cf5cf03ed52f043827804ccf333abc5c&lang=en&cache-only=0",
      "phonetic_am_text": "e.pi.lei.tēr",
      "img": "https://cdn.langeek.co/photo/29854/original/?type=jpeg",
      "pronunciation": "ˈɛpɪlˌeɪɾɚ",
      "senses": [
        {
          "definition": "a device used for removing hair from the root by mechanically grasping and pulling it out",
          "examples": []
        }
      ]
    },
    {
      "id": "7cfd9670-757b-4277-bca2-b41705f43fa5",
      "word": "nose wax",
      "pos": "noun",
      "phonetic": "https://tts.langeek.co/read?text=bm9zZSB3YXg&hash=afa8a2281d318d07fa43b6b5747376c9b3e17d65&lang=en&cache-only=0",
      "phonetic_text": "noʊz wæks",
      "phonetic_am": "https://tts.langeek.co/read?text=bm9zZSB3YXg&hash=afa8a2281d318d07fa43b6b5747376c9b3e17d65&lang=en&cache-only=0",
      "phonetic_am_text": "noooz vāks",
      "img": "",
      "pronunciation": "noʊz wæks",
      "senses": [
        {
          "definition": "a specialized waxing treatment for removing unwanted hair from inside the nostrils, providing a temporary solution for nasal hair removal",
          "examples": [
            {
              "cf": "",
              "x": "The salon offers a quick and painless nose wax for clients looking to tidy up their appearance."
            },
            {
              "cf": "",
              "x": "He decided to try a nose wax for the first time before his big job interview."
            },
            {
              "cf": "",
              "x": "A nose wax can help remove unwanted hair and leave the nostrils feeling clean."
            },
            {
              "cf": "",
              "x": "The beauty technician recommended a nose wax as part of the grooming package."
            },
            {
              "cf": "",
              "x": "Many people find that a nose wax is a more effective solution than trimming with scissors."
            }
          ]
        }
      ]
    },
    {
      "id": "9f6f25d8-7a19-4d54-b115-fccc9dd47c14",
      "word": "wax ready-strip",
      "pos": "noun",
      "phonetic": "https://tts.langeek.co/read?text=d2F4IHJlYWR5LXN0cmlw&hash=e526dfcc406b8c80da119d3b50ef4bf75eddda10&lang=en&cache-only=0",
      "phonetic_text": "wæks rɛ.di-strɪp",
      "phonetic_am": "https://tts.langeek.co/read?text=d2F4IHJlYWR5LXN0cmlw&hash=e526dfcc406b8c80da119d3b50ef4bf75eddda10&lang=en&cache-only=0",
      "phonetic_am_text": "vāks re.di-strip",
      "img": "",
      "pronunciation": "wæks ɹɛdistɹɪp",
      "senses": [
        {
          "definition": "a pre-made strip with wax applied, offering a convenient option for at-home hair removal",
          "examples": []
        }
      ]
    },
    {
      "id": "359a6228-cd04-4173-b890-a2ffbdebe3c6",
      "word": "shaving foam",
      "pos": "noun",
      "phonetic": "https://tts.langeek.co/read?text=c2hhdmluZyBmb2Ft&hash=d752533114236f8db1fde23221ce853dc1557cbd&lang=en&cache-only=0",
      "phonetic_text": "ʃeɪ.vɪng foʊm",
      "phonetic_am": "https://tts.langeek.co/read?text=c2hhdmluZyBmb2Ft&hash=d752533114236f8db1fde23221ce853dc1557cbd&lang=en&cache-only=0",
      "phonetic_am_text": "shei.ving fooom",
      "img": "https://cdn.langeek.co/photo/35645/original/?type=jpeg",
      "pronunciation": "ʃˈeɪvɪŋ fˈoʊm",
      "senses": [
        {
          "definition": "a foamy substance applied to the skin during shaving to provide lubrication and protection for a smoother shave",
          "examples": [
            {
              "cf": "",
              "x": "He applied shaving foam to his face before using the razor."
            },
            {
              "cf": "",
              "x": "The shaving foam helped reduce nicks and cuts while shaving."
            },
            {
              "cf": "",
              "x": "She preferred using shaving foam with a calming scent for a relaxing experience."
            },
            {
              "cf": "",
              "x": "He always keeps an extra can of shaving foam in his travel bag."
            },
            {
              "cf": "",
              "x": "He rinsed his face with warm water after removing the shaving foam."
            }
          ]
        }
      ]
    }
  ]
}