{
  "topic": "amounts",
  "title": "Intensity or Emphasis",
  "lesson": "lesson_2",
  "word_list": [
    {
      "word": "like nobody's business",
      "pos": "None",
      "phonetic": "https://tts.langeek.co/read?text=bGlrZSBub2JvZHkncyBidXNpbmVzcw&hash=218af97e3a10e78c5db1b5ba898c71cbf96de236&lang=en&cache-only=0",
      "phonetic_text": null,
      "phonetic_am": "https://tts.langeek.co/read?text=bGlrZSBub2JvZHkncyBidXNpbmVzcw&hash=218af97e3a10e78c5db1b5ba898c71cbf96de236&lang=en&cache-only=0",
      "phonetic_am_text": null,
      "img": "https://cdn.langeek.co/photo/51340/original/?type=jpeg",
      "pronunciation": "lˈaɪk nˈoʊbɑːdiz bˈɪznəs",
      "senses": [
        {
          "definition": "in a way that is very high in speed, quality, or degree",
          "examples": [
            {
              "cf": "",
              "x": "She can design computer programs like nobody's business."
            },
            {
              "cf": "",
              "x": "The other team came out and dominated our players like nobody's business."
            },
            {
              "cf": "",
              "x": "She can cook like nobody's business; her dishes are always delicious."
            }
          ]
        }
      ]
    },
    {
      "word": "like the Devil",
      "pos": "None",
      "phonetic": "https://tts.langeek.co/read?text=bGlrZSB0aGUgRGV2aWw&hash=dbd15f8d0723d3cdaa47ef5e7402821415481c6e&lang=en&cache-only=0",
      "phonetic_text": null,
      "phonetic_am": "https://tts.langeek.co/read?text=bGlrZSB0aGUgRGV2aWw&hash=dbd15f8d0723d3cdaa47ef5e7402821415481c6e&lang=en&cache-only=0",
      "phonetic_am_text": null,
      "img": "https://cdn.langeek.co/photo/21483/original/?type=jpeg",
      "pronunciation": "lˈaɪk ðə dˈɛvəl",
      "senses": [
        {
          "definition": "in a very intense, energetic, or fast way",
          "examples": [
            {
              "cf": "",
              "x": "She was chopping vegetables like the Devil to get dinner ready in time."
            },
            {
              "cf": "",
              "x": "The storm was raging like the Devil, with strong winds and heavy rain."
            }
          ]
        }
      ]
    },
    {
      "word": "[take] the edge off {sth}",
      "pos": "None",
      "phonetic": "https://tts.langeek.co/read?text=dG8gdGFrZSB0aGUgZWRnZSBvZmYgc29tZXRoaW5n&hash=492b8e37a153437aa6dca791adeaf6457e29f46c&lang=en&cache-only=0",
      "phonetic_text": null,
      "phonetic_am": "https://tts.langeek.co/read?text=dG8gdGFrZSB0aGUgZWRnZSBvZmYgc29tZXRoaW5n&hash=492b8e37a153437aa6dca791adeaf6457e29f46c&lang=en&cache-only=0",
      "phonetic_am_text": null,
      "img": "https://cdn.langeek.co/photo/45110/original/?type=jpeg",
      "pronunciation": "tˈeɪk ðɪ ˈɛdʒ ˈɔf ˌɛstˌiːˈeɪtʃ",
      "senses": [
        {
          "definition": "to make something, particularly something unpleasant, less severe or intense",
          "examples": [
            {
              "cf": "",
              "x": "Listening to soothing music can take the edge off your stress and anxiety."
            },
            {
              "cf": "",
              "x": "Having a light snack before dinner can take the edge off your hunger."
            },
            {
              "cf": "",
              "x": "A warm bath can take the edge off muscle soreness after a workout."
            },
            {
              "cf": "",
              "x": "Laughing with friends can take the edge off a difficult situation."
            }
          ]
        }
      ]
    },
    {
      "word": "[take] the sting out of {sth}",
      "pos": "None",
      "phonetic": "https://tts.langeek.co/read?text=dG8gdGFrZSB0aGUgc3Rpbmcgb3V0IG9mIHNvbWV0aGluZw&hash=42ddd5014f3b25993146ce458070b7c8ed7d21bc&lang=en&cache-only=0",
      "phonetic_text": null,
      "phonetic_am": "https://tts.langeek.co/read?text=dG8gdGFrZSB0aGUgc3Rpbmcgb3V0IG9mIHNvbWV0aGluZw&hash=42ddd5014f3b25993146ce458070b7c8ed7d21bc&lang=en&cache-only=0",
      "phonetic_am_text": null,
      "img": "https://cdn.langeek.co/photo/45112/original/?type=jpeg",
      "pronunciation": "tˈeɪk ðə stˈɪŋ ˌaʊɾəv ˌɛstˌiːˈeɪtʃ",
      "senses": [
        {
          "definition": "to take away from the intensity of something unpleasant",
          "examples": [
            {
              "cf": "",
              "x": "The manager offered extra time off to take the sting out of the mandatory overtime."
            },
            {
              "cf": "",
              "x": "Adding a bit of humor to a difficult conversation can take the sting out of the message."
            },
            {
              "cf": "",
              "x": "The financial assistance program aims to take the sting out of unexpected medical expenses."
            },
            {
              "cf": "",
              "x": "Applying a cold compress can take the sting out of a sunburn."
            }
          ]
        }
      ]
    },
    {
      "word": "according to cocker",
      "pos": "None",
      "phonetic": "https://tts.langeek.co/read?text=YWNjb3JkaW5nIHRvIGNvY2tlcg&hash=59ff6c5f325ae99ce22242d38aaf2f43b0f6bd98&lang=en&cache-only=0",
      "phonetic_text": null,
      "phonetic_am": "https://tts.langeek.co/read?text=YWNjb3JkaW5nIHRvIGNvY2tlcg&hash=59ff6c5f325ae99ce22242d38aaf2f43b0f6bd98&lang=en&cache-only=0",
      "phonetic_am_text": null,
      "img": "https://cdn.langeek.co/photo/48227/original/?type=jpeg",
      "pronunciation": "ɐkˈoːɹdɪŋ tə kˈɑːkɚ",
      "senses": [
        {
          "definition": "in a proper and correct way",
          "examples": []
        }
      ]
    },
    {
      "word": "all the way",
      "pos": "None",
      "phonetic": "https://tts.langeek.co/read?text=YWxsIHRoZSB3YXk&hash=f631d856a7ee20a9c5bd3c4f80dcb23e591303e2&lang=en&cache-only=0",
      "phonetic_text": null,
      "phonetic_am": "https://tts.langeek.co/read?text=YWxsIHRoZSB3YXk&hash=f631d856a7ee20a9c5bd3c4f80dcb23e591303e2&lang=en&cache-only=0",
      "phonetic_am_text": null,
      "img": "https://cdn.langeek.co/photo/45098/original/?type=jpeg",
      "pronunciation": "ˈɔːl ðə wˈeɪ",
      "senses": [
        {
          "definition": "in a complete manner",
          "examples": [
            {
              "cf": "",
              "x": "They supported him all the way through his challenging recovery process."
            },
            {
              "cf": "",
              "x": "She dedicated herself to her studies and earned top grades all the way through school."
            },
            {
              "cf": "",
              "x": "The team gave their best effort all the way through the championship game."
            },
            {
              "cf": "",
              "x": "He pursued his dream of becoming an astronaut all the way, overcoming many obstacles."
            },
            {
              "cf": "",
              "x": "The project was a success because everyone worked diligently all the way to meet the deadline."
            }
          ]
        }
      ]
    },
    {
      "word": "body and soul",
      "pos": "None",
      "phonetic": "https://tts.langeek.co/read?text=Ym9keSBhbmQgc291bA&hash=3751a17ad532a5f07a74630807fe5416dd55d320&lang=en&cache-only=0",
      "phonetic_text": null,
      "phonetic_am": "https://tts.langeek.co/read?text=Ym9keSBhbmQgc291bA&hash=3751a17ad532a5f07a74630807fe5416dd55d320&lang=en&cache-only=0",
      "phonetic_am_text": null,
      "img": "https://cdn.langeek.co/photo/45136/original/?type=jpeg",
      "pronunciation": "bˈɑːdi ænd sˈoʊl",
      "senses": [
        {
          "definition": "with all that one has",
          "examples": [
            {
              "cf": "",
              "x": "She was now committed to the band, body and soul."
            },
            {
              "cf": "",
              "x": "She dedicated herself to the cause, body and soul, working tirelessly to make a difference."
            },
            {
              "cf": "",
              "x": "They fell in love with each other, connecting on a level that touched them both, body and soul."
            },
            {
              "cf": "",
              "x": "The artist poured his creativity into his work, expressing himself fully, body and soul."
            },
            {
              "cf": "",
              "x": "She pursued her passion for music with unwavering dedication, giving it her all, body and soul."
            }
          ]
        }
      ]
    },
    {
      "word": "neck and crop",
      "pos": "None",
      "phonetic": "https://tts.langeek.co/read?text=bmVjayBhbmQgY3JvcA&hash=7a6416362dab565afdbc83af8b08b9adf5bf9214&lang=en&cache-only=0",
      "phonetic_text": null,
      "phonetic_am": "https://tts.langeek.co/read?text=bmVjayBhbmQgY3JvcA&hash=7a6416362dab565afdbc83af8b08b9adf5bf9214&lang=en&cache-only=0",
      "phonetic_am_text": null,
      "img": "https://cdn.langeek.co/photo/45144/original/?type=jpeg",
      "pronunciation": "nˈɛk ænd kɹˈɑːp",
      "senses": [
        {
          "definition": "completely and in every possible way",
          "examples": [
            {
              "cf": "",
              "x": "They devoured the cake, eating it neck and crop, leaving no slices behind."
            },
            {
              "cf": "",
              "x": "He finished the assignment neck and crop, ensuring every task was completed."
            },
            {
              "cf": "",
              "x": "She sold her old belongings at the garage sale, clearing out the house neck and crop."
            },
            {
              "cf": "",
              "x": "The company restructured its operations, revamping the entire system neck and crop."
            },
            {
              "cf": "",
              "x": "He read the novel in one sitting, enjoying it neck and crop."
            }
          ]
        }
      ]
    },
    {
      "word": "smack dab",
      "pos": "adverb",
      "phonetic": "https://tts.langeek.co/read?text=c21hY2sgZGFi&hash=abe4858ab848ffd5a89dbe208bb7832aaa3f6e65&lang=en&cache-only=0",
      "phonetic_text": null,
      "phonetic_am": "https://tts.langeek.co/read?text=c21hY2sgZGFi&hash=abe4858ab848ffd5a89dbe208bb7832aaa3f6e65&lang=en&cache-only=0",
      "phonetic_am_text": null,
      "img": "https://cdn.langeek.co/photo/23673/original/?type=jpeg",
      "pronunciation": "smˈæk dˈæb",
      "senses": [
        {
          "definition": "in a precise and exact way",
          "examples": [
            {
              "cf": "",
              "x": "The car hit the pothole and the tire blew out, leaving us smack dab in the middle of the road."
            },
            {
              "cf": "",
              "x": "She placed the cake on the table smack dab in the center for everyone to admire."
            },
            {
              "cf": "",
              "x": "I found the missing key on the floor, smack dab in the middle of the living room."
            },
            {
              "cf": "",
              "x": "The restaurant is located smack dab in the heart of downtown, making it convenient for tourists."
            },
            {
              "cf": "",
              "x": "The painting hung on the wall is smack dab above the fireplace, making it a focal point in the room."
            }
          ]
        }
      ]
    },
    {
      "word": "on the nose",
      "pos": "None",
      "phonetic": "https://tts.langeek.co/read?text=b24gdGhlIG5vc2U&hash=fd0d7793f71595c0eb2d23e8553219b3f1ee7c9f&lang=en&cache-only=0",
      "phonetic_text": null,
      "phonetic_am": "https://tts.langeek.co/read?text=b24gdGhlIG5vc2U&hash=fd0d7793f71595c0eb2d23e8553219b3f1ee7c9f&lang=en&cache-only=0",
      "phonetic_am_text": null,
      "img": "https://cdn.langeek.co/photo/28742/original/?type=jpeg",
      "pronunciation": "ɑːnðə nˈoʊz",
      "senses": [
        {
          "definition": "used for emphasizing the correctness or accuracy of something",
          "examples": [
            {
              "cf": "",
              "x": "His estimate for the project completion date was right on the nose; it finished exactly when he predicted."
            },
            {
              "cf": "",
              "x": "The temperature reached the forecasted high of 90 degrees on the nose."
            },
            {
              "cf": "",
              "x": "The chef's seasoning was on the nose; the dish had the perfect amount of flavor."
            },
            {
              "cf": "",
              "x": "The actor's portrayal of the character was on the nose; it captured every nuance perfectly."
            },
            {
              "cf": "",
              "x": "She guessed the number of jellybeans in the jar on the nose; there were exactly 200."
            }
          ]
        }
      ]
    },
    {
      "word": "out and out",
      "pos": "None",
      "phonetic": "https://tts.langeek.co/read?text=b3V0IGFuZCBvdXQ&hash=f5a59b0751be7ae2f8990e0cd0c128702b9b039b&lang=en&cache-only=0",
      "phonetic_text": null,
      "phonetic_am": "https://tts.langeek.co/read?text=b3V0IGFuZCBvdXQ&hash=f5a59b0751be7ae2f8990e0cd0c128702b9b039b&lang=en&cache-only=0",
      "phonetic_am_text": null,
      "img": "https://cdn.langeek.co/photo/45146/original/?type=jpeg",
      "pronunciation": "ˈaʊt ænd ˈaʊt",
      "senses": [
        {
          "definition": "in a complete and total way",
          "examples": [
            {
              "cf": "",
              "x": "He was induced to part out and out with all the money."
            },
            {
              "cf": "",
              "x": "She's an out and out professional, always delivering high-quality work."
            },
            {
              "cf": "",
              "x": "The concert was an out and out success, with the audience cheering for an encore."
            }
          ]
        }
      ]
    },
    {
      "word": "the hell out of {sth}",
      "pos": "None",
      "phonetic": "https://tts.langeek.co/read?text=dGhlIGhlbGwgb3V0IG9mIHNvbWV0aGluZw&hash=314d75228450523e21a49742a096b06cdb0acf8b&lang=en&cache-only=0",
      "phonetic_text": null,
      "phonetic_am": "https://tts.langeek.co/read?text=dGhlIGhlbGwgb3V0IG9mIHNvbWV0aGluZw&hash=314d75228450523e21a49742a096b06cdb0acf8b&lang=en&cache-only=0",
      "phonetic_am_text": null,
      "img": "https://cdn.langeek.co/photo/45140/original/?type=jpeg",
      "pronunciation": "ðə hˈɛl ˌaʊɾəv ˌɛstˌiːˈeɪtʃ",
      "senses": [
        {
          "definition": "used for emphasizing the intensity, speed, etc. of something",
          "examples": [
            {
              "cf": "",
              "x": "She laughed the hell out of that joke, couldn't stop giggling for hours."
            },
            {
              "cf": "",
              "x": "He worked the hell out of that project to meet the tight deadline."
            },
            {
              "cf": "",
              "x": "They partied the hell out of the weekend, dancing and celebrating."
            },
            {
              "cf": "",
              "x": "Don't nag him about it; he's studying the hell out of those textbooks."
            }
          ]
        }
      ]
    },
    {
      "word": "through and through",
      "pos": "None",
      "phonetic": "https://tts.langeek.co/read?text=dGhyb3VnaCBhbmQgdGhyb3VnaA&hash=659d2b217bcdfa26b2ebdb087a436caec1655272&lang=en&cache-only=0",
      "phonetic_text": null,
      "phonetic_am": "https://tts.langeek.co/read?text=dGhyb3VnaCBhbmQgdGhyb3VnaA&hash=659d2b217bcdfa26b2ebdb087a436caec1655272&lang=en&cache-only=0",
      "phonetic_am_text": null,
      "img": "https://cdn.langeek.co/photo/45156/original/?type=jpeg",
      "pronunciation": "θɹuː ænd θɹˈuː",
      "senses": [
        {
          "definition": "in every single way",
          "examples": [
            {
              "cf": "",
              "x": "She's a New Yorker through and through, with her accent and love for the city."
            },
            {
              "cf": "",
              "x": "The soldier was loyal to his country through and through, even in the face of danger."
            },
            {
              "cf": "",
              "x": "He's a dedicated musician through and through, always composing or playing his instruments."
            },
            {
              "cf": "",
              "x": "She's a vegetarian through and through, never consuming any meat or animal products."
            },
            {
              "cf": "",
              "x": "The detective was determined to solve the case through and through, leaving no stone unturned."
            }
          ]
        }
      ]
    },
    {
      "word": "for the thousandth time",
      "pos": "None",
      "phonetic": "https://tts.langeek.co/read?text=Zm9yIHRoZSB0aG91c2FuZHRoIHRpbWU&hash=a89c9018d7d02a89828be788dfefe49ba840eccc&lang=en&cache-only=0",
      "phonetic_text": null,
      "phonetic_am": "https://tts.langeek.co/read?text=Zm9yIHRoZSB0aG91c2FuZHRoIHRpbWU&hash=a89c9018d7d02a89828be788dfefe49ba840eccc&lang=en&cache-only=0",
      "phonetic_am_text": null,
      "img": "https://cdn.langeek.co/photo/45138/original/?type=jpeg",
      "pronunciation": "fɚðə θˈaʊzəndθ tˈaɪm",
      "senses": [
        {
          "definition": "used to emphasize that one has done or said something many times in the past",
          "examples": [
            {
              "cf": "",
              "x": "I'm telling you for the thousandth time, I had nothing to do with it."
            },
            {
              "cf": "",
              "x": "Your phone is ringing for the thousandth time."
            },
            {
              "cf": "",
              "x": "I've told you for the thousandth time to clean up your room!"
            },
            {
              "cf": "",
              "x": "For the thousandth time, please remember to turn off the lights when you leave"
            }
          ]
        }
      ]
    },
    {
      "word": "the mother of all {sth}",
      "pos": "None",
      "phonetic": "https://tts.langeek.co/read?text=dGhlIG1vdGhlciBvZiBhbGwgc29tZXRoaW5n&hash=742b35c5af654774fb4a5f85d33870c80d51285e&lang=en&cache-only=0",
      "phonetic_text": null,
      "phonetic_am": "https://tts.langeek.co/read?text=dGhlIG1vdGhlciBvZiBhbGwgc29tZXRoaW5n&hash=742b35c5af654774fb4a5f85d33870c80d51285e&lang=en&cache-only=0",
      "phonetic_am_text": null,
      "img": "https://cdn.langeek.co/photo/45242/original/?type=jpeg",
      "pronunciation": "ðə mˈʌðɚɹ ʌv ˈɔːl ˌɛstˌiːˈeɪtʃ",
      "senses": [
        {
          "definition": "used to describe the intensity of something",
          "examples": [
            {
              "cf": "",
              "x": "I got stuck in the mother of all traffic jams."
            },
            {
              "cf": "",
              "x": "I woke up with the mother of all hangovers."
            },
            {
              "cf": "",
              "x": "\"That was the mother of all storms; I've never seen such heavy rain."
            },
            {
              "cf": "",
              "x": "The project is the mother of all challenges; it will require all of our resources."
            },
            {
              "cf": "",
              "x": "The traffic jam on the freeway is the mother of all traffic jams; we'll be stuck for hours."
            }
          ]
        }
      ]
    },
    {
      "word": "the shit out of {sb/sth}",
      "pos": "None",
      "phonetic": "https://tts.langeek.co/read?text=dGhlIHNoaXQgb3V0IG9mIHNvbWVib2R5IG9yIHNvbWV0aGluZw&hash=eda5c08f968de9e60d3d11bd5437d018edd2292e&lang=en&cache-only=0",
      "phonetic_text": null,
      "phonetic_am": "https://tts.langeek.co/read?text=dGhlIHNoaXQgb3V0IG9mIHNvbWVib2R5IG9yIHNvbWV0aGluZw&hash=eda5c08f968de9e60d3d11bd5437d018edd2292e&lang=en&cache-only=0",
      "phonetic_am_text": null,
      "img": "https://cdn.langeek.co/photo/45154/original/?type=jpeg",
      "pronunciation": "ðə ʃˈɪt ˌaʊɾəv ˌɛsbˈiː slˈæʃ ˌɛstˌiːˈeɪtʃ",
      "senses": [
        {
          "definition": "used to emphasize that someone does something with excessive intensity or force",
          "examples": [
            {
              "cf": "",
              "x": "He studied the shit out of that textbook before the exam."
            },
            {
              "cf": "",
              "x": "I cleaned the shit out of my apartment before my guests arrived."
            },
            {
              "cf": "",
              "x": "She trained the shit out of her body for the marathon."
            },
            {
              "cf": "",
              "x": "He played the guitar like he was born to do it, shredding the shit out of that solo."
            }
          ]
        }
      ]
    }
  ]
}